{
  "catalog_id": "EP-027",
  "category": "MMM-Episoden",
  "title": "Episode 027: Hamsternator",
  "release_date": "2005-07-29",
  "authors": [
    "Agent Cat"
  ],
  "forum_thread_url_mmm": null,
  "wiki_url_mmm": "http://wiki.maniac-mansion-mania.de/wiki/Hamsternator",
  "walkthrough_url": null,
  "mmm_description": null,
  "forum_thread_url_adventure_treff": "https://www.adventure-treff.de/forum/topic/7000",
  "forum_thread_url_adventure_treff_legacy": "http://www.adventure-treff.de/forum/viewtopic.php?t=7000",
  "youtube_longplay_url": "https://www.youtube.com/watch?v=jVhawLzeh-U&list=PLF3YnSazju8E_2kO3nKy7oloZHG80C5l5&index=44",
  "download_url_mmm_docman": "http://www.maniac-mansion-mania.com/index.php?option=com_docman&task=doc_download&gid=29",
  "download_url_mmm_canonical": "https://www.maniac-mansion-mania.de/downloads/episoden/staffel3/mmm27.zip",
  "release_package_filename": "mmm27.zip",
  "release_package_stemname": "mmm27",
  "game_files_subpath": null,
  "engine": "AGS",
  "engine_version": "2.61.747",
  "mirror_url_github_private": "https://github.com/selloa/mmm-mirror-poc-7k3xq/releases/download/v1/mmm27.zip",
  "mirror_url_dropbox_public": "https://www.dropbox.com/scl/fi/z994d5qaldzdbhca4uh9p/mmm27.zip?rlkey=dreu5dkj276aoyzdj1qta5jsz&dl=1"
}
